<?xml version="1.0" encoding="utf-8" ?>
<dwsync>
<file name="financialtaxplanning.cfc" server="https://ftp.awensa.com/MS/MS0213/" local="130313385725934965" remote="130313385740000000" />
<file name="financialtaxplanning.cfm" server="https://ftp.awensa.com/MS/MS0213/" local="130313740793912978" remote="130313740910000000" />
<file name="financialtaxplanning.js" server="https://ftp.awensa.com/MS/MS0213/" local="130313382845840233" remote="130313385470000000" />
<file name="notices.cfc" server="https://ftp.awensa.com/MS/MS0213/" local="130313386865660154" remote="130313386890000000" />
<file name="notices.cfm" server="https://ftp.awensa.com/MS/MS0213/" local="130313741015389602" remote="130313741060000000" />
<file name="notices.js" server="https://ftp.awensa.com/MS/MS0213/" local="130313388449870766" remote="130313388470000000" />
<file name="powerofattorney.cfc" server="https://ftp.awensa.com/MS/MS0213/" local="130313386644487504" remote="130313386770000000" />
<file name="powerofattorney.cfm" server="https://ftp.awensa.com/MS/MS0213/" local="130313387920950513" remote="130313387930000000" />
<file name="powerofattorney.js" server="https://ftp.awensa.com/MS/MS0213/" local="130313388524295022" remote="130313388540000000" />
<file name="taxreturns.js" server="https://ftp.awensa.com/MS/MS0213/" local="130313426172828395" remote="130313426260000000" />
<file name="taxreturns.cfm" server="https://ftp.awensa.com/MS/MS0213/" local="130313741253614717" remote="130313741300000000" />
<file name="taxreturns.cfc" server="https://ftp.awensa.com/MS/MS0213/" local="130313427209377683" remote="130313427240000000" />
</dwsync>