<?xml version="1.0" encoding="utf-8" ?>
<dwsync>
<file name="payrollpayrollchecks.js" server="https://ftp.awensa.com/MS/MS0213/" local="130232967178480868" remote="130232977240000000" />
<file name="payrollpayrollchecks.cfc" server="https://ftp.awensa.com/MS/MS0213/" local="130232967178440866" remote="130232977200000000" />
<file name="payrollPayrollChecks.cfm" server="https://ftp.awensa.com/MS/MS0213/" local="130233969556409496" remote="130233970410000000" />
<file name="payrollotherfilingrequirements.js" server="https://ftp.awensa.com/MS/MS0213/" local="130222840224143420" remote="130232977200000000" />
<file name="payrollOtherFilingsRequirements.cfm" server="https://ftp.awensa.com/MS/MS0213/" local="130233969424951977" remote="130233970500000000" />
<file name="payrollotherfilingrequirements.cfc" server="https://ftp.awensa.com/MS/MS0213/" local="130228022488050891" remote="130232977200000000" />
<file name="payrollPayrollTaxes.cfm" server="https://ftp.awensa.com/MS/MS0213/" local="130233969719288812" remote="130233970360000000" />
<file name="payrollpayrolltaxes.js" server="https://ftp.awensa.com/MS/MS0213/" local="130227109273514424" remote="130232977290000000" />
<file name="payrollpayrolltaxes.cfc" server="https://ftp.awensa.com/MS/MS0213/" local="130227109273474421" remote="130232977240000000" />
<file name="_payrolltaxes.css" server="https://ftp.awensa.com/MS/MS0213/" local="130233932146799789" remote="130233932180000000" />
<file name="payrollreporting.cfc" server="https://ftp.awensa.com/MS/MS0213/" local="130195787312626119" remote="130232977340000000" />
<file name="payrollReporting.cfm" server="https://ftp.awensa.com/MS/MS0213/" local="130232969458431274" remote="130232977340000000" />
<file name="payrollreporting.js" server="https://ftp.awensa.com/MS/MS0213/" local="130195787312636120" remote="130232977340000000" />
<file name="payrolreporting.cfm" server="https://ftp.awensa.com/MS/MS0213/" local="130232969458711290" remote="130232977340000000" />
</dwsync>