<?xml version="1.0" encoding="utf-8" ?>
<dwsync>
<file name="add.png" server="https://ftp.awensa.com/MS/MS0213/" local="130192495845228563" remote="130245987950000000" Dst="2" />
<file name="close.png" server="https://ftp.awensa.com/MS/MS0213/" local="130192495845378571" remote="130245988060000000" Dst="2" />
<file name="column-asc.png" server="https://ftp.awensa.com/MS/MS0213/" local="130192495845388572" remote="130245988110000000" Dst="2" />
<file name="column-desc.png" server="https://ftp.awensa.com/MS/MS0213/" local="130192495845388572" remote="130245988110000000" Dst="2" />
<file name="column-sortable.png" server="https://ftp.awensa.com/MS/MS0213/" local="130192495845398572" remote="130245988110000000" Dst="2" />
<file name="delete.png" server="https://ftp.awensa.com/MS/MS0213/" local="130192495845648587" remote="130245988260000000" Dst="2" />
<file name="edit.png" server="https://ftp.awensa.com/MS/MS0213/" local="130192495845648587" remote="130245988260000000" Dst="2" />
<file name="jtable_metro_base.css" server="https://ftp.awensa.com/MS/MS0213/" local="130245983819326495" remote="130245988410000000" Dst="2" />
<file name="jtable_metro_base.less" server="https://ftp.awensa.com/MS/MS0213/" local="130192495845788595" remote="130245988410000000" Dst="2" />
<file name="jtable_metro_base.min.css" server="https://ftp.awensa.com/MS/MS0213/" local="130245983819846525" remote="130245988410000000" Dst="2" />
</dwsync>